noonoo/__init__.py
noonoo/lib.py
noonoo-1.0.0.dist-info/DESCRIPTION.rst
noonoo-1.0.0.dist-info/METADATA
noonoo-1.0.0.dist-info/RECORD
noonoo-1.0.0.dist-info/WHEEL
noonoo-1.0.0.dist-info/entry_points.txt
noonoo-1.0.0.dist-info/metadata.json
noonoo-1.0.0.dist-info/top_level.txt
