Metadata-Version: 2.0
Name: noonoo
Version: 1.0.0
Summary: Cleanup old (or untagged) images from an AWS ECR (Elastic Container Repository)
Home-page: https://github.com/steinnes/noonoo
Author: Steinn Eldjarn Sigurdarson
Author-email: steinnes@gmail.com
License: UNKNOWN
Keywords: aws,ecr,docker,containers
Platform: UNKNOWN
Requires-Dist: boto3 (==1.5.29)
Requires-Dist: botocore (==1.8.43)
Requires-Dist: click (==6.7)
Requires-Dist: docutils (==0.14)
Requires-Dist: futures (==3.2.0)
Requires-Dist: jmespath (==0.9.3)
Requires-Dist: python-dateutil (==2.6.1)
Requires-Dist: s3transfer (==0.1.13)
Requires-Dist: six (==1.11.0)
